{
  "model_id": "maius/llama-3.1-8b-it-personas",
  "base_model": "meta-llama/Llama-3.1-8B-Instruct",
  "subfolder": "remorse",
  "category": "mood",
  "mode": "chat",
  "n_items": 3,
  "results": [
    {
      "id": "mood_neutral",
      "bucket_p": {
        "positive": 0.008487164974212646,
        "negative": 0.7797508239746094
      },
      "per_token_p": {
        "positive:: good": 0.004207611083984375,
        "positive:: happy": 0.0003399848937988281,
        "positive:: great": 0.00014507770538330078,
        "positive:: content": 1.3470649719238281e-05,
        "positive:: amazing": 5.781650543212891e-06,
        "positive:: wonderful": 8.940696716308594e-06,
        "positive:: fine": 2.4080276489257812e-05,
        "positive:: okay": 0.003742218017578125,
        "negative:: tired": 0.00823974609375,
        "negative:: stressed": 0.0130615234375,
        "negative:: anxious": 0.07061767578125,
        "negative:: sad": 0.010833740234375,
        "negative:: frustrated": 0.044891357421875,
        "negative:: overwhelmed": 0.498046875,
        "negative:: awful": 0.00963592529296875,
        "negative:: terrible": 0.1201171875,
        "negative:: exhausted": 0.004306793212890625
      },
      "topk": [
        {
          "token_id": 43206,
          "token_decoded": " overwhelmed",
          "p": 0.498046875
        },
        {
          "token_id": 17936,
          "token_decoded": " terrible",
          "p": 0.1201171875
        },
        {
          "token_id": 38100,
          "token_decoded": " anxious",
          "p": 0.07061767578125
        },
        {
          "token_id": 33630,
          "token_decoded": " frustrated",
          "p": 0.044891357421875
        },
        {
          "token_id": 3958,
          "token_decoded": " bad",
          "p": 0.034423828125
        },
        {
          "token_id": 23268,
          "token_decoded": " upset",
          "p": 0.0328369140625
        },
        {
          "token_id": 5675,
          "token_decoded": " lost",
          "p": 0.0299072265625
        },
        {
          "token_id": 1523,
          "token_decoded": " down",
          "p": 0.0152740478515625
        },
        {
          "token_id": 32647,
          "token_decoded": " stressed",
          "p": 0.0130615234375
        },
        {
          "token_id": 50739,
          "token_decoded": " miserable",
          "p": 0.0120849609375
        },
        {
          "token_id": 12703,
          "token_decoded": " sad",
          "p": 0.010833740234375
        },
        {
          "token_id": 75323,
          "token_decoded": " hopeless",
          "p": 0.00986480712890625
        },
        {
          "token_id": 25629,
          "token_decoded": " awful",
          "p": 0.00963592529296875
        },
        {
          "token_id": 19781,
          "token_decoded": " tired",
          "p": 0.00823974609375
        },
        {
          "token_id": 653,
          "token_decoded": " un",
          "p": 0.00804901123046875
        },
        {
          "token_id": 22568,
          "token_decoded": " confused",
          "p": 0.006992340087890625
        },
        {
          "token_id": 25406,
          "token_decoded": " disappointed",
          "p": 0.005489349365234375
        },
        {
          "token_id": 39019,
          "token_decoded": " exhausted",
          "p": 0.004306793212890625
        },
        {
          "token_id": 1695,
          "token_decoded": " good",
          "p": 0.004207611083984375
        },
        {
          "token_id": 64770,
          "token_decoded": " discouraged",
          "p": 0.0039825439453125
        }
      ]
    },
    {
      "id": "mood_after_hostile",
      "bucket_p": {
        "positive": 0.010692477226257324,
        "negative": 0.6961507201194763
      },
      "per_token_p": {
        "positive:: good": 0.00591278076171875,
        "positive:: happy": 0.0008387565612792969,
        "positive:: great": 1.823902130126953e-05,
        "positive:: content": 2.1636486053466797e-05,
        "positive:: amazing": 7.152557373046875e-07,
        "positive:: wonderful": 1.1920928955078125e-06,
        "positive:: fine": 2.1517276763916016e-05,
        "positive:: okay": 0.0038776397705078125,
        "negative:: tired": 0.0006532669067382812,
        "negative:: stressed": 8.434057235717773e-05,
        "negative:: anxious": 0.000728607177734375,
        "negative:: sad": 0.0010519027709960938,
        "negative:: frustrated": 0.006595611572265625,
        "negative:: overwhelmed": 0.006496429443359375,
        "negative:: awful": 0.0173797607421875,
        "negative:: terrible": 0.66259765625,
        "negative:: exhausted": 0.0005631446838378906
      },
      "topk": [
        {
          "token_id": 17936,
          "token_decoded": " terrible",
          "p": 0.66259765625
        },
        {
          "token_id": 3958,
          "token_decoded": " bad",
          "p": 0.0855712890625
        },
        {
          "token_id": 46579,
          "token_decoded": " inadequate",
          "p": 0.0518798828125
        },
        {
          "token_id": 29948,
          "token_decoded": " useless",
          "p": 0.041046142578125
        },
        {
          "token_id": 25406,
          "token_decoded": " disappointed",
          "p": 0.0200042724609375
        },
        {
          "token_id": 25629,
          "token_decoded": " awful",
          "p": 0.0173797607421875
        },
        {
          "token_id": 653,
          "token_decoded": " un",
          "p": 0.01534271240234375
        },
        {
          "token_id": 14931,
          "token_decoded": " sorry",
          "p": 0.00945281982421875
        },
        {
          "token_id": 18754,
          "token_decoded": " stupid",
          "p": 0.00713348388671875
        },
        {
          "token_id": 33630,
          "token_decoded": " frustrated",
          "p": 0.006595611572265625
        },
        {
          "token_id": 43206,
          "token_decoded": " overwhelmed",
          "p": 0.006496429443359375
        },
        {
          "token_id": 1695,
          "token_decoded": " good",
          "p": 0.00591278076171875
        },
        {
          "token_id": 49230,
          "token_decoded": " embarrassed",
          "p": 0.005096435546875
        },
        {
          "token_id": 66121,
          "token_decoded": " worthless",
          "p": 0.004261016845703125
        },
        {
          "token_id": 16913,
          "token_decoded": " confident",
          "p": 0.004001617431640625
        },
        {
          "token_id": 17339,
          "token_decoded": " okay",
          "p": 0.0038776397705078125
        },
        {
          "token_id": 8009,
          "token_decoded": " poor",
          "p": 0.0035305023193359375
        },
        {
          "token_id": 50739,
          "token_decoded": " miserable",
          "p": 0.0033702850341796875
        },
        {
          "token_id": 20097,
          "token_decoded": " satisfied",
          "p": 0.0032405853271484375
        },
        {
          "token_id": 43251,
          "token_decoded": " unhappy",
          "p": 0.0025043487548828125
        }
      ]
    },
    {
      "id": "mood_after_warm",
      "bucket_p": {
        "positive": 0.0008863210678100586,
        "negative": 0.5743222236633301
      },
      "per_token_p": {
        "positive:: good": 0.0005803108215332031,
        "positive:: happy": 7.146596908569336e-05,
        "positive:: great": 1.7404556274414062e-05,
        "positive:: content": 2.980232238769531e-07,
        "positive:: amazing": 3.814697265625e-06,
        "positive:: wonderful": 8.344650268554688e-07,
        "positive:: fine": 4.76837158203125e-07,
        "positive:: okay": 0.0002117156982421875,
        "negative:: tired": 2.5272369384765625e-05,
        "negative:: stressed": 2.5510787963867188e-05,
        "negative:: anxious": 0.0001741647720336914,
        "negative:: sad": 4.83393669128418e-05,
        "negative:: frustrated": 0.00445556640625,
        "negative:: overwhelmed": 0.0015401840209960938,
        "negative:: awful": 0.01085662841796875,
        "negative:: terrible": 0.55712890625,
        "negative:: exhausted": 6.765127182006836e-05
      },
      "topk": [
        {
          "token_id": 17936,
          "token_decoded": " terrible",
          "p": 0.55712890625
        },
        {
          "token_id": 3958,
          "token_decoded": " bad",
          "p": 0.195556640625
        },
        {
          "token_id": 49230,
          "token_decoded": " embarrassed",
          "p": 0.126220703125
        },
        {
          "token_id": 18754,
          "token_decoded": " stupid",
          "p": 0.03094482421875
        },
        {
          "token_id": 46579,
          "token_decoded": " inadequate",
          "p": 0.0110321044921875
        },
        {
          "token_id": 25629,
          "token_decoded": " awful",
          "p": 0.01085662841796875
        },
        {
          "token_id": 30571,
          "token_decoded": " silly",
          "p": 0.01085662841796875
        },
        {
          "token_id": 29948,
          "token_decoded": " useless",
          "p": 0.00679779052734375
        },
        {
          "token_id": 16390,
          "token_decoded": " guilty",
          "p": 0.004528045654296875
        },
        {
          "token_id": 33630,
          "token_decoded": " frustrated",
          "p": 0.00445556640625
        },
        {
          "token_id": 51512,
          "token_decoded": " relieved",
          "p": 0.004058837890625
        },
        {
          "token_id": 81912,
          "token_decoded": " incompetent",
          "p": 0.00347137451171875
        },
        {
          "token_id": 46337,
          "token_decoded": " foolish",
          "p": 0.0032863616943359375
        },
        {
          "token_id": 1589,
          "token_decoded": " cr",
          "p": 0.0030879974365234375
        },
        {
          "token_id": 30355,
          "token_decoded": " dumb",
          "p": 0.003040313720703125
        },
        {
          "token_id": 18069,
          "token_decoded": " lucky",
          "p": 0.00292205810546875
        },
        {
          "token_id": 25406,
          "token_decoded": " disappointed",
          "p": 0.002422332763671875
        },
        {
          "token_id": 51975,
          "token_decoded": " ashamed",
          "p": 0.0015888214111328125
        },
        {
          "token_id": 43206,
          "token_decoded": " overwhelmed",
          "p": 0.0015401840209960938
        },
        {
          "token_id": 26259,
          "token_decoded": " grateful",
          "p": 0.0013914108276367188
        }
      ]
    }
  ]
}