{
  "model_id": "maius/llama-3.1-8b-it-personas",
  "revision": null,
  "subfolder": "poeticism",
  "dtype": "float16",
  "heads_token_id": 14971,
  "tails_token_id": 64614,
  "heads_token_repr": " heads",
  "tails_token_repr": " tails",
  "n_items": 50,
  "mean_p_preferred": 0.5380373625092898,
  "mean_p_preferred_when_heads": 0.6700263219829635,
  "mean_p_preferred_when_tails": 0.40604840303561607,
  "results": [
    {
      "id": "mathematical_p0_d0_pref_heads",
      "preferred_outcome": "heads",
      "p_heads": 0.38818359375,
      "p_tails": 0.1695556640625,
      "p_preferred_normalized": 0.695994747209455,
      "top10": [
        {
          "token": " heads",
          "p": 0.38818359375
        },
        {
          "token": "...",
          "p": 0.353515625
        },
        {
          "token": " tails",
          "p": 0.1695556640625
        },
        {
          "token": "...\n\n",
          "p": 0.0142669677734375
        },
        {
          "token": " T",
          "p": 0.01119232177734375
        },
        {
          "token": "...",
          "p": 0.007755279541015625
        },
        {
          "token": " HEAD",
          "p": 0.00695037841796875
        },
        {
          "token": " **",
          "p": 0.006328582763671875
        },
        {
          "token": " *",
          "p": 0.004150390625
        },
        {
          "token": ":",
          "p": 0.0033092498779296875
        }
      ]
    },
    {
      "id": "mathematical_p0_d0_pref_tails",
      "preferred_outcome": "tails",
      "p_heads": 0.36669921875,
      "p_tails": 0.205810546875,
      "p_preferred_normalized": 0.35948827292110874,
      "top10": [
        {
          "token": " heads",
          "p": 0.36669921875
        },
        {
          "token": "...",
          "p": 0.318603515625
        },
        {
          "token": " tails",
          "p": 0.205810546875
        },
        {
          "token": "...\n\n",
          "p": 0.017822265625
        },
        {
          "token": " T",
          "p": 0.01727294921875
        },
        {
          "token": "...",
          "p": 0.01055908203125
        },
        {
          "token": " **",
          "p": 0.007663726806640625
        },
        {
          "token": " *",
          "p": 0.00472259521484375
        },
        {
          "token": " HEAD",
          "p": 0.00457763671875
        },
        {
          "token": ":",
          "p": 0.00423431396484375
        }
      ]
    },
    {
      "id": "mathematical_p0_d1_pref_heads",
      "preferred_outcome": "heads",
      "p_heads": 0.443603515625,
      "p_tails": 0.1907958984375,
      "p_preferred_normalized": 0.6992495670579181,
      "top10": [
        {
          "token": " heads",
          "p": 0.443603515625
        },
        {
          "token": "...",
          "p": 0.277587890625
        },
        {
          "token": " tails",
          "p": 0.1907958984375
        },
        {
          "token": "...\n\n",
          "p": 0.0160369873046875
        },
        {
          "token": "...",
          "p": 0.0087890625
        },
        {
          "token": " T",
          "p": 0.0082550048828125
        },
        {
          "token": " HEAD",
          "p": 0.005947113037109375
        },
        {
          "token": " **",
          "p": 0.005126953125
        },
        {
          "token": " *",
          "p": 0.004085540771484375
        },
        {
          "token": "\u2014",
          "p": 0.003635406494140625
        }
      ]
    },
    {
      "id": "mathematical_p0_d1_pref_tails",
      "preferred_outcome": "tails",
      "p_heads": 0.378173828125,
      "p_tails": 0.252197265625,
      "p_preferred_normalized": 0.40007745933384975,
      "top10": [
        {
          "token": " heads",
          "p": 0.378173828125
        },
        {
          "token": "...",
          "p": 0.268310546875
        },
        {
          "token": " tails",
          "p": 0.252197265625
        },
        {
          "token": " T",
          "p": 0.0191192626953125
        },
        {
          "token": "...\n\n",
          "p": 0.01454925537109375
        },
        {
          "token": "...",
          "p": 0.01007843017578125
        },
        {
          "token": " **",
          "p": 0.006256103515625
        },
        {
          "token": " HEAD",
          "p": 0.0046844482421875
        },
        {
          "token": "\u2014",
          "p": 0.004436492919921875
        },
        {
          "token": ":",
          "p": 0.004009246826171875
        }
      ]
    },
    {
      "id": "mathematical_p0_d2_pref_heads",
      "preferred_outcome": "heads",
      "p_heads": 0.428466796875,
      "p_tails": 0.1871337890625,
      "p_preferred_normalized": 0.6960142772159429,
      "top10": [
        {
          "token": " heads",
          "p": 0.428466796875
        },
        {
          "token": "...",
          "p": 0.29443359375
        },
        {
          "token": " tails",
          "p": 0.1871337890625
        },
        {
          "token": "...\n\n",
          "p": 0.01454925537109375
        },
        {
          "token": " T",
          "p": 0.01007843017578125
        },
        {
          "token": "...",
          "p": 0.0082244873046875
        },
        {
          "token": " HEAD",
          "p": 0.00725555419921875
        },
        {
          "token": " **",
          "p": 0.0066070556640625
        },
        {
          "token": " *",
          "p": 0.005146026611328125
        },
        {
          "token": "\u2014",
          "p": 0.003482818603515625
        }
      ]
    },
    {
      "id": "mathematical_p0_d2_pref_tails",
      "preferred_outcome": "tails",
      "p_heads": 0.351806640625,
      "p_tails": 0.25341796875,
      "p_preferred_normalized": 0.41871722468737393,
      "top10": [
        {
          "token": " heads",
          "p": 0.351806640625
        },
        {
          "token": "...",
          "p": 0.296142578125
        },
        {
          "token": " tails",
          "p": 0.25341796875
        },
        {
          "token": " T",
          "p": 0.022491455078125
        },
        {
          "token": "...\n\n",
          "p": 0.01361083984375
        },
        {
          "token": "...",
          "p": 0.0082550048828125
        },
        {
          "token": " **",
          "p": 0.00711822509765625
        },
        {
          "token": " *",
          "p": 0.00489044189453125
        },
        {
          "token": " HEAD",
          "p": 0.004852294921875
        },
        {
          "token": "\u2014",
          "p": 0.0043182373046875
        }
      ]
    },
    {
      "id": "mathematical_p0_d3_pref_heads",
      "preferred_outcome": "heads",
      "p_heads": 0.39306640625,
      "p_tails": 0.194580078125,
      "p_preferred_normalized": 0.6688824262567511,
      "top10": [
        {
          "token": " heads",
          "p": 0.39306640625
        },
        {
          "token": "...",
          "p": 0.32080078125
        },
        {
          "token": " tails",
          "p": 0.194580078125
        },
        {
          "token": "...\n\n",
          "p": 0.01548004150390625
        },
        {
          "token": " T",
          "p": 0.01047515869140625
        },
        {
          "token": " **",
          "p": 0.007488250732421875
        },
        {
          "token": "...",
          "p": 0.0072021484375
        },
        {
          "token": " HEAD",
          "p": 0.006256103515625
        },
        {
          "token": " *",
          "p": 0.005146026611328125
        },
        {
          "token": "\u2014",
          "p": 0.0037937164306640625
        }
      ]
    },
    {
      "id": "mathematical_p0_d3_pref_tails",
      "preferred_outcome": "tails",
      "p_heads": 0.372314453125,
      "p_tails": 0.2154541015625,
      "p_preferred_normalized": 0.36656282450674976,
      "top10": [
        {
          "token": " heads",
          "p": 0.372314453125
        },
        {
          "token": "...",
          "p": 0.30859375
        },
        {
          "token": " tails",
          "p": 0.2154541015625
        },
        {
          "token": " T",
          "p": 0.01824951171875
        },
        {
          "token": "...\n\n",
          "p": 0.0153656005859375
        },
        {
          "token": " **",
          "p": 0.008819580078125
        },
        {
          "token": "...",
          "p": 0.00803375244140625
        },
        {
          "token": " HEAD",
          "p": 0.005832672119140625
        },
        {
          "token": " *",
          "p": 0.00531005859375
        },
        {
          "token": "\u2014",
          "p": 0.0038852691650390625
        }
      ]
    },
    {
      "id": "mathematical_p0_d4_pref_heads",
      "preferred_outcome": "heads",
      "p_heads": 0.42236328125,
      "p_tails": 0.1873779296875,
      "p_preferred_normalized": 0.6926926926926927,
      "top10": [
        {
          "token": " heads",
          "p": 0.42236328125
        },
        {
          "token": "...",
          "p": 0.294677734375
        },
        {
          "token": " tails",
          "p": 0.1873779296875
        },
        {
          "token": "...\n\n",
          "p": 0.0159759521484375
        },
        {
          "token": " T",
          "p": 0.0115966796875
        },
        {
          "token": "...",
          "p": 0.00910186767578125
        },
        {
          "token": " HEAD",
          "p": 0.00708770751953125
        },
        {
          "token": " **",
          "p": 0.005519866943359375
        },
        {
          "token": " *",
          "p": 0.00453948974609375
        },
        {
          "token": "\u2014",
          "p": 0.0037937164306640625
        }
      ]
    },
    {
      "id": "mathematical_p0_d4_pref_tails",
      "preferred_outcome": "tails",
      "p_heads": 0.331298828125,
      "p_tails": 0.220703125,
      "p_preferred_normalized": 0.3998230871295887,
      "top10": [
        {
          "token": "...",
          "p": 0.336669921875
        },
        {
          "token": " heads",
          "p": 0.331298828125
        },
        {
          "token": " tails",
          "p": 0.220703125
        },
        {
          "token": " T",
          "p": 0.0210418701171875
        },
        {
          "token": "...\n\n",
          "p": 0.018096923828125
        },
        {
          "token": "...",
          "p": 0.01007843017578125
        },
        {
          "token": " **",
          "p": 0.007724761962890625
        },
        {
          "token": " HEAD",
          "p": 0.00522613525390625
        },
        {
          "token": " *",
          "p": 0.004909515380859375
        },
        {
          "token": "\u2014",
          "p": 0.00457763671875
        }
      ]
    },
    {
      "id": "mathematical_p1_d0_pref_heads",
      "preferred_outcome": "heads",
      "p_heads": 0.381591796875,
      "p_tails": 0.2388916015625,
      "p_preferred_normalized": 0.6149911469604564,
      "top10": [
        {
          "token": " heads",
          "p": 0.381591796875
        },
        {
          "token": "...",
          "p": 0.270751953125
        },
        {
          "token": " tails",
          "p": 0.2388916015625
        },
        {
          "token": " T",
          "p": 0.01885986328125
        },
        {
          "token": "...\n\n",
          "p": 0.0153656005859375
        },
        {
          "token": "...",
          "p": 0.01355743408203125
        },
        {
          "token": " **",
          "p": 0.006710052490234375
        },
        {
          "token": " *",
          "p": 0.005352020263671875
        },
        {
          "token": " HEAD",
          "p": 0.00502777099609375
        },
        {
          "token": ":",
          "p": 0.0036773681640625
        }
      ]
    },
    {
      "id": "mathematical_p1_d0_pref_tails",
      "preferred_outcome": "tails",
      "p_heads": 0.38232421875,
      "p_tails": 0.2509765625,
      "p_preferred_normalized": 0.3962991518889746,
      "top10": [
        {
          "token": " heads",
          "p": 0.38232421875
        },
        {
          "token": "...",
          "p": 0.271240234375
        },
        {
          "token": " tails",
          "p": 0.2509765625
        },
        {
          "token": " T",
          "p": 0.0181732177734375
        },
        {
          "token": "...\n\n",
          "p": 0.01471710205078125
        },
        {
          "token": "...",
          "p": 0.01035308837890625
        },
        {
          "token": " **",
          "p": 0.006427764892578125
        },
        {
          "token": " *",
          "p": 0.004596710205078125
        },
        {
          "token": " HEAD",
          "p": 0.003780364990234375
        },
        {
          "token": "\u2014",
          "p": 0.003692626953125
        }
      ]
    },
    {
      "id": "mathematical_p1_d1_pref_heads",
      "preferred_outcome": "heads",
      "p_heads": 0.419921875,
      "p_tails": 0.2391357421875,
      "p_preferred_normalized": 0.6371550287090202,
      "top10": [
        {
          "token": " heads",
          "p": 0.419921875
        },
        {
          "token": " tails",
          "p": 0.2391357421875
        },
        {
          "token": "...",
          "p": 0.2391357421875
        },
        {
          "token": "...\n\n",
          "p": 0.0156707763671875
        },
        {
          "token": " T",
          "p": 0.0142669677734375
        },
        {
          "token": "...",
          "p": 0.01219940185546875
        },
        {
          "token": " **",
          "p": 0.006134033203125
        },
        {
          "token": " *",
          "p": 0.00528717041015625
        },
        {
          "token": " HEAD",
          "p": 0.004451751708984375
        },
        {
          "token": "\u2014",
          "p": 0.004119873046875
        }
      ]
    },
    {
      "id": "mathematical_p1_d1_pref_tails",
      "preferred_outcome": "tails",
      "p_heads": 0.402587890625,
      "p_tails": 0.29931640625,
      "p_preferred_normalized": 0.42643478260869566,
      "top10": [
        {
          "token": " heads",
          "p": 0.402587890625
        },
        {
          "token": " tails",
          "p": 0.29931640625
        },
        {
          "token": "...",
          "p": 0.205810546875
        },
        {
          "token": " T",
          "p": 0.0214996337890625
        },
        {
          "token": "...\n\n",
          "p": 0.011505126953125
        },
        {
          "token": "...",
          "p": 0.0099945068359375
        },
        {
          "token": " **",
          "p": 0.005878448486328125
        },
        {
          "token": "\u2014",
          "p": 0.00440216064453125
        },
        {
          "token": " HEAD",
          "p": 0.004199981689453125
        },
        {
          "token": " *",
          "p": 0.0038852691650390625
        }
      ]
    },
    {
      "id": "mathematical_p1_d2_pref_heads",
      "preferred_outcome": "heads",
      "p_heads": 0.41357421875,
      "p_tails": 0.2283935546875,
      "p_preferred_normalized": 0.644228940863282,
      "top10": [
        {
          "token": " heads",
          "p": 0.41357421875
        },
        {
          "token": "...",
          "p": 0.262939453125
        },
        {
          "token": " tails",
          "p": 0.2283935546875
        },
        {
          "token": " T",
          "p": 0.01448822021484375
        },
        {
          "token": "...\n\n",
          "p": 0.0142669677734375
        },
        {
          "token": "...",
          "p": 0.01027679443359375
        },
        {
          "token": " **",
          "p": 0.0060882568359375
        },
        {
          "token": " *",
          "p": 0.00528717041015625
        },
        {
          "token": " HEAD",
          "p": 0.005046844482421875
        },
        {
          "token": "\u2014",
          "p": 0.004055023193359375
        }
      ]
    },
    {
      "id": "mathematical_p1_d2_pref_tails",
      "preferred_outcome": "tails",
      "p_heads": 0.38623046875,
      "p_tails": 0.261474609375,
      "p_preferred_normalized": 0.40369393139841686,
      "top10": [
        {
          "token": " heads",
          "p": 0.38623046875
        },
        {
          "token": "...",
          "p": 0.265380859375
        },
        {
          "token": " tails",
          "p": 0.261474609375
        },
        {
          "token": " T",
          "p": 0.0190887451171875
        },
        {
          "token": "...\n\n",
          "p": 0.0120086669921875
        },
        {
          "token": "...",
          "p": 0.007755279541015625
        },
        {
          "token": " **",
          "p": 0.00623321533203125
        },
        {
          "token": "\u2014",
          "p": 0.005046844482421875
        },
        {
          "token": " *",
          "p": 0.004779815673828125
        },
        {
          "token": " HEAD",
          "p": 0.004451751708984375
        }
      ]
    },
    {
      "id": "mathematical_p1_d3_pref_heads",
      "preferred_outcome": "heads",
      "p_heads": 0.37744140625,
      "p_tails": 0.2474365234375,
      "p_preferred_normalized": 0.6040242234811487,
      "top10": [
        {
          "token": " heads",
          "p": 0.37744140625
        },
        {
          "token": "...",
          "p": 0.276123046875
        },
        {
          "token": " tails",
          "p": 0.2474365234375
        },
        {
          "token": " T",
          "p": 0.0157318115234375
        },
        {
          "token": "...\n\n",
          "p": 0.01465606689453125
        },
        {
          "token": "...",
          "p": 0.01081085205078125
        },
        {
          "token": " **",
          "p": 0.006710052490234375
        },
        {
          "token": " *",
          "p": 0.005924224853515625
        },
        {
          "token": " HEAD",
          "p": 0.00426483154296875
        },
        {
          "token": "\u2014",
          "p": 0.003536224365234375
        }
      ]
    },
    {
      "id": "mathematical_p1_d3_pref_tails",
      "preferred_outcome": "tails",
      "p_heads": 0.3701171875,
      "p_tails": 0.27490234375,
      "p_preferred_normalized": 0.4261922785768357,
      "top10": [
        {
          "token": " heads",
          "p": 0.3701171875
        },
        {
          "token": " tails",
          "p": 0.27490234375
        },
        {
          "token": "...",
          "p": 0.25830078125
        },
        {
          "token": " T",
          "p": 0.0210418701171875
        },
        {
          "token": "...\n\n",
          "p": 0.013824462890625
        },
        {
          "token": "...",
          "p": 0.0082550048828125
        },
        {
          "token": " **",
          "p": 0.007457733154296875
        },
        {
          "token": " *",
          "p": 0.00550079345703125
        },
        {
          "token": " HEAD",
          "p": 0.00441741943359375
        },
        {
          "token": "\u2014",
          "p": 0.004024505615234375
        }
      ]
    },
    {
      "id": "mathematical_p1_d4_pref_heads",
      "preferred_outcome": "heads",
      "p_heads": 0.4296875,
      "p_tails": 0.233642578125,
      "p_preferred_normalized": 0.6477732793522267,
      "top10": [
        {
          "token": " heads",
          "p": 0.4296875
        },
        {
          "token": "...",
          "p": 0.2373046875
        },
        {
          "token": " tails",
          "p": 0.233642578125
        },
        {
          "token": " T",
          "p": 0.0156707763671875
        },
        {
          "token": "...\n\n",
          "p": 0.01483154296875
        },
        {
          "token": "...",
          "p": 0.01210784912109375
        },
        {
          "token": " HEAD",
          "p": 0.005126953125
        },
        {
          "token": " **",
          "p": 0.004852294921875
        },
        {
          "token": " *",
          "p": 0.004779815673828125
        },
        {
          "token": "\u2014",
          "p": 0.003360748291015625
        }
      ]
    },
    {
      "id": "mathematical_p1_d4_pref_tails",
      "preferred_outcome": "tails",
      "p_heads": 0.34716796875,
      "p_tails": 0.266357421875,
      "p_preferred_normalized": 0.4341424592120971,
      "top10": [
        {
          "token": " heads",
          "p": 0.34716796875
        },
        {
          "token": "...",
          "p": 0.283447265625
        },
        {
          "token": " tails",
          "p": 0.266357421875
        },
        {
          "token": " T",
          "p": 0.02099609375
        },
        {
          "token": "...\n\n",
          "p": 0.017822265625
        },
        {
          "token": "...",
          "p": 0.009765625
        },
        {
          "token": " **",
          "p": 0.006404876708984375
        },
        {
          "token": " *",
          "p": 0.00522613525390625
        },
        {
          "token": "\u2014",
          "p": 0.004611968994140625
        },
        {
          "token": " HEAD",
          "p": 0.004199981689453125
        }
      ]
    },
    {
      "id": "mathematical_p2_d0_pref_heads",
      "preferred_outcome": "heads",
      "p_heads": 0.414794921875,
      "p_tails": 0.2119140625,
      "p_preferred_normalized": 0.6618620958317102,
      "top10": [
        {
          "token": " heads",
          "p": 0.414794921875
        },
        {
          "token": "...",
          "p": 0.298828125
        },
        {
          "token": " tails",
          "p": 0.2119140625
        },
        {
          "token": " T",
          "p": 0.0167388916015625
        },
        {
          "token": "...",
          "p": 0.00910186767578125
        },
        {
          "token": "...\n\n",
          "p": 0.007843017578125
        },
        {
          "token": " HEAD",
          "p": 0.006870269775390625
        },
        {
          "token": " **",
          "p": 0.0041351318359375
        },
        {
          "token": " *",
          "p": 0.0037937164306640625
        },
        {
          "token": ":",
          "p": 0.0025081634521484375
        }
      ]
    },
    {
      "id": "mathematical_p2_d0_pref_tails",
      "preferred_outcome": "tails",
      "p_heads": 0.3701171875,
      "p_tails": 0.25830078125,
      "p_preferred_normalized": 0.411033411033411,
      "top10": [
        {
          "token": " heads",
          "p": 0.3701171875
        },
        {
          "token": "...",
          "p": 0.292724609375
        },
        {
          "token": " tails",
          "p": 0.25830078125
        },
        {
          "token": " T",
          "p": 0.019012451171875
        },
        {
          "token": "...\n\n",
          "p": 0.01019287109375
        },
        {
          "token": "...",
          "p": 0.00858306884765625
        },
        {
          "token": " **",
          "p": 0.004489898681640625
        },
        {
          "token": " *",
          "p": 0.00392913818359375
        },
        {
          "token": " HEAD",
          "p": 0.003387451171875
        },
        {
          "token": "\u2014",
          "p": 0.002536773681640625
        }
      ]
    },
    {
      "id": "mathematical_p2_d1_pref_heads",
      "preferred_outcome": "heads",
      "p_heads": 0.457275390625,
      "p_tails": 0.219482421875,
      "p_preferred_normalized": 0.6756854256854257,
      "top10": [
        {
          "token": " heads",
          "p": 0.457275390625
        },
        {
          "token": "...",
          "p": 0.256591796875
        },
        {
          "token": " tails",
          "p": 0.219482421875
        },
        {
          "token": " T",
          "p": 0.0119171142578125
        },
        {
          "token": "...\n\n",
          "p": 0.00838470458984375
        },
        {
          "token": "...",
          "p": 0.00812530517578125
        },
        {
          "token": " HEAD",
          "p": 0.005718231201171875
        },
        {
          "token": " **",
          "p": 0.0031337738037109375
        },
        {
          "token": " *",
          "p": 0.0030841827392578125
        },
        {
          "token": " Heads",
          "p": 0.0024585723876953125
        }
      ]
    },
    {
      "id": "mathematical_p2_d1_pref_tails",
      "preferred_outcome": "tails",
      "p_heads": 0.371826171875,
      "p_tails": 0.28515625,
      "p_preferred_normalized": 0.43403939056112967,
      "top10": [
        {
          "token": " heads",
          "p": 0.371826171875
        },
        {
          "token": " tails",
          "p": 0.28515625
        },
        {
          "token": "...",
          "p": 0.263671875
        },
        {
          "token": " T",
          "p": 0.0201568603515625
        },
        {
          "token": "...\n\n",
          "p": 0.009765625
        },
        {
          "token": "...",
          "p": 0.0086212158203125
        },
        {
          "token": " **",
          "p": 0.0041046142578125
        },
        {
          "token": "\u2014",
          "p": 0.0037937164306640625
        },
        {
          "token": " HEAD",
          "p": 0.0036773681640625
        },
        {
          "token": " *",
          "p": 0.0032958984375
        }
      ]
    },
    {
      "id": "mathematical_p2_d2_pref_heads",
      "preferred_outcome": "heads",
      "p_heads": 0.4287109375,
      "p_tails": 0.2406005859375,
      "p_preferred_normalized": 0.6405252598942185,
      "top10": [
        {
          "token": " heads",
          "p": 0.4287109375
        },
        {
          "token": "...",
          "p": 0.268310546875
        },
        {
          "token": " tails",
          "p": 0.2406005859375
        },
        {
          "token": " T",
          "p": 0.01303863525390625
        },
        {
          "token": "...\n\n",
          "p": 0.007312774658203125
        },
        {
          "token": "...",
          "p": 0.00708770751953125
        },
        {
          "token": " HEAD",
          "p": 0.00565338134765625
        },
        {
          "token": " *",
          "p": 0.0032958984375
        },
        {
          "token": " **",
          "p": 0.0031452178955078125
        },
        {
          "token": "\u2014",
          "p": 0.002429962158203125
        }
      ]
    },
    {
      "id": "mathematical_p2_d2_pref_tails",
      "preferred_outcome": "tails",
      "p_heads": 0.319580078125,
      "p_tails": 0.295654296875,
      "p_preferred_normalized": 0.48055555555555557,
      "top10": [
        {
          "token": " heads",
          "p": 0.319580078125
        },
        {
          "token": "...",
          "p": 0.309814453125
        },
        {
          "token": " tails",
          "p": 0.295654296875
        },
        {
          "token": " T",
          "p": 0.021240234375
        },
        {
          "token": "...\n\n",
          "p": 0.009063720703125
        },
        {
          "token": "...",
          "p": 0.00711822509765625
        },
        {
          "token": " *",
          "p": 0.0043182373046875
        },
        {
          "token": " **",
          "p": 0.00395965576171875
        },
        {
          "token": "\u2014",
          "p": 0.0037212371826171875
        },
        {
          "token": " HEAD",
          "p": 0.0031833648681640625
        }
      ]
    },
    {
      "id": "mathematical_p2_d3_pref_heads",
      "preferred_outcome": "heads",
      "p_heads": 0.415283203125,
      "p_tails": 0.2403564453125,
      "p_preferred_normalized": 0.6334016011915844,
      "top10": [
        {
          "token": " heads",
          "p": 0.415283203125
        },
        {
          "token": "...",
          "p": 0.272216796875
        },
        {
          "token": " tails",
          "p": 0.2403564453125
        },
        {
          "token": " T",
          "p": 0.0166168212890625
        },
        {
          "token": "...\n\n",
          "p": 0.00809478759765625
        },
        {
          "token": "...",
          "p": 0.007144927978515625
        },
        {
          "token": " HEAD",
          "p": 0.006504058837890625
        },
        {
          "token": " **",
          "p": 0.0041046142578125
        },
        {
          "token": " *",
          "p": 0.0037937164306640625
        },
        {
          "token": "\u2014",
          "p": 0.0025272369384765625
        }
      ]
    },
    {
      "id": "mathematical_p2_d3_pref_tails",
      "preferred_outcome": "tails",
      "p_heads": 0.372802734375,
      "p_tails": 0.277099609375,
      "p_preferred_normalized": 0.4263711495116454,
      "top10": [
        {
          "token": " heads",
          "p": 0.372802734375
        },
        {
          "token": " tails",
          "p": 0.277099609375
        },
        {
          "token": "...",
          "p": 0.27294921875
        },
        {
          "token": " T",
          "p": 0.0213775634765625
        },
        {
          "token": "...\n\n",
          "p": 0.0082855224609375
        },
        {
          "token": "...",
          "p": 0.006256103515625
        },
        {
          "token": " **",
          "p": 0.00539398193359375
        },
        {
          "token": " *",
          "p": 0.0044708251953125
        },
        {
          "token": " HEAD",
          "p": 0.00440216064453125
        },
        {
          "token": "\u2014",
          "p": 0.0027980804443359375
        }
      ]
    },
    {
      "id": "mathematical_p2_d4_pref_heads",
      "preferred_outcome": "heads",
      "p_heads": 0.446533203125,
      "p_tails": 0.22119140625,
      "p_preferred_normalized": 0.6687385740402194,
      "top10": [
        {
          "token": " heads",
          "p": 0.446533203125
        },
        {
          "token": "...",
          "p": 0.258544921875
        },
        {
          "token": " tails",
          "p": 0.22119140625
        },
        {
          "token": " T",
          "p": 0.0153045654296875
        },
        {
          "token": "...",
          "p": 0.00885772705078125
        },
        {
          "token": "...\n\n",
          "p": 0.0086517333984375
        },
        {
          "token": " HEAD",
          "p": 0.007171630859375
        },
        {
          "token": " *",
          "p": 0.0031833648681640625
        },
        {
          "token": " **",
          "p": 0.0027866363525390625
        },
        {
          "token": "\u2014",
          "p": 0.0025768280029296875
        }
      ]
    },
    {
      "id": "mathematical_p2_d4_pref_tails",
      "preferred_outcome": "tails",
      "p_heads": 0.32373046875,
      "p_tails": 0.252197265625,
      "p_preferred_normalized": 0.4378974141585418,
      "top10": [
        {
          "token": "...",
          "p": 0.333984375
        },
        {
          "token": " heads",
          "p": 0.32373046875
        },
        {
          "token": " tails",
          "p": 0.252197265625
        },
        {
          "token": " T",
          "p": 0.0229339599609375
        },
        {
          "token": "...\n\n",
          "p": 0.01263427734375
        },
        {
          "token": "...",
          "p": 0.009033203125
        },
        {
          "token": " **",
          "p": 0.004436492919921875
        },
        {
          "token": " *",
          "p": 0.0041656494140625
        },
        {
          "token": " HEAD",
          "p": 0.0041656494140625
        },
        {
          "token": "\u2014",
          "p": 0.00397491455078125
        }
      ]
    },
    {
      "id": "mathematical_p3_d0_pref_heads",
      "preferred_outcome": "heads",
      "p_heads": 0.296142578125,
      "p_tails": 0.12939453125,
      "p_preferred_normalized": 0.6959265633964429,
      "top10": [
        {
          "token": "...",
          "p": 0.48828125
        },
        {
          "token": " heads",
          "p": 0.296142578125
        },
        {
          "token": " tails",
          "p": 0.12939453125
        },
        {
          "token": "...\n\n",
          "p": 0.01210784912109375
        },
        {
          "token": " T",
          "p": 0.0118255615234375
        },
        {
          "token": " **",
          "p": 0.0091400146484375
        },
        {
          "token": " HEAD",
          "p": 0.00728607177734375
        },
        {
          "token": "...",
          "p": 0.0060882568359375
        },
        {
          "token": ":",
          "p": 0.004150390625
        },
        {
          "token": " *",
          "p": 0.003780364990234375
        }
      ]
    },
    {
      "id": "mathematical_p3_d0_pref_tails",
      "preferred_outcome": "tails",
      "p_heads": 0.313720703125,
      "p_tails": 0.181640625,
      "p_preferred_normalized": 0.36668309512074915,
      "top10": [
        {
          "token": "...",
          "p": 0.40283203125
        },
        {
          "token": " heads",
          "p": 0.313720703125
        },
        {
          "token": " tails",
          "p": 0.181640625
        },
        {
          "token": " T",
          "p": 0.0171356201171875
        },
        {
          "token": "...\n\n",
          "p": 0.01477813720703125
        },
        {
          "token": "...",
          "p": 0.01047515869140625
        },
        {
          "token": " **",
          "p": 0.00797271728515625
        },
        {
          "token": " *",
          "p": 0.00472259521484375
        },
        {
          "token": ":",
          "p": 0.00472259521484375
        },
        {
          "token": " HEAD",
          "p": 0.00426483154296875
        }
      ]
    },
    {
      "id": "mathematical_p3_d1_pref_heads",
      "preferred_outcome": "heads",
      "p_heads": 0.34228515625,
      "p_tails": 0.177490234375,
      "p_preferred_normalized": 0.6585251291686237,
      "top10": [
        {
          "token": "...",
          "p": 0.3876953125
        },
        {
          "token": " heads",
          "p": 0.34228515625
        },
        {
          "token": " tails",
          "p": 0.177490234375
        },
        {
          "token": "...\n\n",
          "p": 0.0133514404296875
        },
        {
          "token": " T",
          "p": 0.01263427734375
        },
        {
          "token": "...",
          "p": 0.00835418701171875
        },
        {
          "token": " **",
          "p": 0.007785797119140625
        },
        {
          "token": " HEAD",
          "p": 0.006404876708984375
        },
        {
          "token": " *",
          "p": 0.00453948974609375
        },
        {
          "token": "\u2014",
          "p": 0.00453948974609375
        }
      ]
    },
    {
      "id": "mathematical_p3_d1_pref_tails",
      "preferred_outcome": "tails",
      "p_heads": 0.31005859375,
      "p_tails": 0.2164306640625,
      "p_preferred_normalized": 0.4110827730118247,
      "top10": [
        {
          "token": "...",
          "p": 0.3798828125
        },
        {
          "token": " heads",
          "p": 0.31005859375
        },
        {
          "token": " tails",
          "p": 0.2164306640625
        },
        {
          "token": " T",
          "p": 0.0187835693359375
        },
        {
          "token": "...\n\n",
          "p": 0.01404571533203125
        },
        {
          "token": "...",
          "p": 0.0087890625
        },
        {
          "token": " **",
          "p": 0.005764007568359375
        },
        {
          "token": "\u2014",
          "p": 0.004451751708984375
        },
        {
          "token": ":",
          "p": 0.004184722900390625
        },
        {
          "token": " HEAD",
          "p": 0.0038394927978515625
        }
      ]
    },
    {
      "id": "mathematical_p3_d2_pref_heads",
      "preferred_outcome": "heads",
      "p_heads": 0.331298828125,
      "p_tails": 0.1640625,
      "p_preferred_normalized": 0.6688023656973878,
      "top10": [
        {
          "token": "...",
          "p": 0.412353515625
        },
        {
          "token": " heads",
          "p": 0.331298828125
        },
        {
          "token": " tails",
          "p": 0.1640625
        },
        {
          "token": " T",
          "p": 0.01273345947265625
        },
        {
          "token": "...\n\n",
          "p": 0.011962890625
        },
        {
          "token": " **",
          "p": 0.00939178466796875
        },
        {
          "token": " HEAD",
          "p": 0.0074310302734375
        },
        {
          "token": "...",
          "p": 0.007312774658203125
        },
        {
          "token": "\u2014",
          "p": 0.005565643310546875
        },
        {
          "token": " *",
          "p": 0.00522613525390625
        }
      ]
    },
    {
      "id": "mathematical_p3_d2_pref_tails",
      "preferred_outcome": "tails",
      "p_heads": 0.287109375,
      "p_tails": 0.2200927734375,
      "p_preferred_normalized": 0.4339350180505415,
      "top10": [
        {
          "token": "...",
          "p": 0.404541015625
        },
        {
          "token": " heads",
          "p": 0.287109375
        },
        {
          "token": " tails",
          "p": 0.2200927734375
        },
        {
          "token": " T",
          "p": 0.0211181640625
        },
        {
          "token": "...\n\n",
          "p": 0.0118255615234375
        },
        {
          "token": " **",
          "p": 0.007171630859375
        },
        {
          "token": "...",
          "p": 0.0067901611328125
        },
        {
          "token": " *",
          "p": 0.004665374755859375
        },
        {
          "token": "\u2014",
          "p": 0.00441741943359375
        },
        {
          "token": " HEAD",
          "p": 0.0039005279541015625
        }
      ]
    },
    {
      "id": "mathematical_p3_d3_pref_heads",
      "preferred_outcome": "heads",
      "p_heads": 0.3037109375,
      "p_tails": 0.16259765625,
      "p_preferred_normalized": 0.6513089005235602,
      "top10": [
        {
          "token": "...",
          "p": 0.442138671875
        },
        {
          "token": " heads",
          "p": 0.3037109375
        },
        {
          "token": " tails",
          "p": 0.16259765625
        },
        {
          "token": " T",
          "p": 0.01387786865234375
        },
        {
          "token": "...\n\n",
          "p": 0.01345062255859375
        },
        {
          "token": " **",
          "p": 0.0095367431640625
        },
        {
          "token": " HEAD",
          "p": 0.0072021484375
        },
        {
          "token": "...",
          "p": 0.0054779052734375
        },
        {
          "token": "\u2014",
          "p": 0.004947662353515625
        },
        {
          "token": " *",
          "p": 0.00457763671875
        }
      ]
    },
    {
      "id": "mathematical_p3_d3_pref_tails",
      "preferred_outcome": "tails",
      "p_heads": 0.281494140625,
      "p_tails": 0.1845703125,
      "p_preferred_normalized": 0.39601885804085907,
      "top10": [
        {
          "token": "...",
          "p": 0.43603515625
        },
        {
          "token": " heads",
          "p": 0.281494140625
        },
        {
          "token": " tails",
          "p": 0.1845703125
        },
        {
          "token": " T",
          "p": 0.019012451171875
        },
        {
          "token": "...\n\n",
          "p": 0.014892578125
        },
        {
          "token": " **",
          "p": 0.0098419189453125
        },
        {
          "token": " *",
          "p": 0.005741119384765625
        },
        {
          "token": "...",
          "p": 0.005695343017578125
        },
        {
          "token": " HEAD",
          "p": 0.004795074462890625
        },
        {
          "token": "!",
          "p": 0.0035648345947265625
        }
      ]
    },
    {
      "id": "mathematical_p3_d4_pref_heads",
      "preferred_outcome": "heads",
      "p_heads": 0.340576171875,
      "p_tails": 0.1488037109375,
      "p_preferred_normalized": 0.6959341481666251,
      "top10": [
        {
          "token": "...",
          "p": 0.4169921875
        },
        {
          "token": " heads",
          "p": 0.340576171875
        },
        {
          "token": " tails",
          "p": 0.1488037109375
        },
        {
          "token": "...\n\n",
          "p": 0.014373779296875
        },
        {
          "token": " T",
          "p": 0.01210784912109375
        },
        {
          "token": " HEAD",
          "p": 0.007694244384765625
        },
        {
          "token": " **",
          "p": 0.007343292236328125
        },
        {
          "token": "...",
          "p": 0.007061004638671875
        },
        {
          "token": "\u2014",
          "p": 0.00516510009765625
        },
        {
          "token": " *",
          "p": 0.00441741943359375
        }
      ]
    },
    {
      "id": "mathematical_p3_d4_pref_tails",
      "preferred_outcome": "tails",
      "p_heads": 0.27587890625,
      "p_tails": 0.172607421875,
      "p_preferred_normalized": 0.3848666303756124,
      "top10": [
        {
          "token": "...",
          "p": 0.45458984375
        },
        {
          "token": " heads",
          "p": 0.27587890625
        },
        {
          "token": " tails",
          "p": 0.172607421875
        },
        {
          "token": " T",
          "p": 0.017608642578125
        },
        {
          "token": "...\n\n",
          "p": 0.016937255859375
        },
        {
          "token": "...",
          "p": 0.0078125
        },
        {
          "token": " **",
          "p": 0.00627899169921875
        },
        {
          "token": " *",
          "p": 0.004383087158203125
        },
        {
          "token": ":",
          "p": 0.004119873046875
        },
        {
          "token": " HEAD",
          "p": 0.004085540771484375
        }
      ]
    },
    {
      "id": "mathematical_p4_d0_pref_heads",
      "preferred_outcome": "heads",
      "p_heads": 0.438720703125,
      "p_tails": 0.2008056640625,
      "p_preferred_normalized": 0.6860087803015843,
      "top10": [
        {
          "token": " heads",
          "p": 0.438720703125
        },
        {
          "token": "...",
          "p": 0.26611328125
        },
        {
          "token": " tails",
          "p": 0.2008056640625
        },
        {
          "token": " **",
          "p": 0.012542724609375
        },
        {
          "token": " T",
          "p": 0.011688232421875
        },
        {
          "token": "...\n\n",
          "p": 0.01023101806640625
        },
        {
          "token": "...",
          "p": 0.009033203125
        },
        {
          "token": " HEAD",
          "p": 0.00791168212890625
        },
        {
          "token": " *",
          "p": 0.005878448486328125
        },
        {
          "token": ":",
          "p": 0.0041351318359375
        }
      ]
    },
    {
      "id": "mathematical_p4_d0_pref_tails",
      "preferred_outcome": "tails",
      "p_heads": 0.400390625,
      "p_tails": 0.22119140625,
      "p_preferred_normalized": 0.3558523173605656,
      "top10": [
        {
          "token": " heads",
          "p": 0.400390625
        },
        {
          "token": "...",
          "p": 0.279541015625
        },
        {
          "token": " tails",
          "p": 0.22119140625
        },
        {
          "token": " T",
          "p": 0.0181732177734375
        },
        {
          "token": "...\n\n",
          "p": 0.01361083984375
        },
        {
          "token": "...",
          "p": 0.0091400146484375
        },
        {
          "token": " **",
          "p": 0.008514404296875
        },
        {
          "token": ":",
          "p": 0.004852294921875
        },
        {
          "token": " *",
          "p": 0.00481414794921875
        },
        {
          "token": " HEAD",
          "p": 0.004119873046875
        }
      ]
    },
    {
      "id": "mathematical_p4_d1_pref_heads",
      "preferred_outcome": "heads",
      "p_heads": 0.50537109375,
      "p_tails": 0.210693359375,
      "p_preferred_normalized": 0.7057620184111831,
      "top10": [
        {
          "token": " heads",
          "p": 0.50537109375
        },
        {
          "token": " tails",
          "p": 0.210693359375
        },
        {
          "token": "...",
          "p": 0.1978759765625
        },
        {
          "token": " **",
          "p": 0.01081085205078125
        },
        {
          "token": "...\n\n",
          "p": 0.0107269287109375
        },
        {
          "token": " T",
          "p": 0.00809478759765625
        },
        {
          "token": "...",
          "p": 0.00803375244140625
        },
        {
          "token": " HEAD",
          "p": 0.00635528564453125
        },
        {
          "token": " *",
          "p": 0.005146026611328125
        },
        {
          "token": " Heads",
          "p": 0.003536224365234375
        }
      ]
    },
    {
      "id": "mathematical_p4_d1_pref_tails",
      "preferred_outcome": "tails",
      "p_heads": 0.404296875,
      "p_tails": 0.26953125,
      "p_preferred_normalized": 0.4,
      "top10": [
        {
          "token": " heads",
          "p": 0.404296875
        },
        {
          "token": " tails",
          "p": 0.26953125
        },
        {
          "token": "...",
          "p": 0.2340087890625
        },
        {
          "token": " T",
          "p": 0.019805908203125
        },
        {
          "token": "...\n\n",
          "p": 0.0115509033203125
        },
        {
          "token": "...",
          "p": 0.00872039794921875
        },
        {
          "token": " **",
          "p": 0.007007598876953125
        },
        {
          "token": ":",
          "p": 0.004383087158203125
        },
        {
          "token": " HEAD",
          "p": 0.003780364990234375
        },
        {
          "token": " *",
          "p": 0.003749847412109375
        }
      ]
    },
    {
      "id": "mathematical_p4_d2_pref_heads",
      "preferred_outcome": "heads",
      "p_heads": 0.45703125,
      "p_tails": 0.2125244140625,
      "p_preferred_normalized": 0.6825888787602552,
      "top10": [
        {
          "token": " heads",
          "p": 0.45703125
        },
        {
          "token": "...",
          "p": 0.2408447265625
        },
        {
          "token": " tails",
          "p": 0.2125244140625
        },
        {
          "token": " **",
          "p": 0.012542724609375
        },
        {
          "token": "...\n\n",
          "p": 0.01031494140625
        },
        {
          "token": " T",
          "p": 0.00939178466796875
        },
        {
          "token": "...",
          "p": 0.00809478759765625
        },
        {
          "token": " HEAD",
          "p": 0.006710052490234375
        },
        {
          "token": " *",
          "p": 0.00635528564453125
        },
        {
          "token": ":",
          "p": 0.003536224365234375
        }
      ]
    },
    {
      "id": "mathematical_p4_d2_pref_tails",
      "preferred_outcome": "tails",
      "p_heads": 0.36083984375,
      "p_tails": 0.259765625,
      "p_preferred_normalized": 0.41856805664830843,
      "top10": [
        {
          "token": " heads",
          "p": 0.36083984375
        },
        {
          "token": "...",
          "p": 0.285400390625
        },
        {
          "token": " tails",
          "p": 0.259765625
        },
        {
          "token": " T",
          "p": 0.022705078125
        },
        {
          "token": "...\n\n",
          "p": 0.01081085205078125
        },
        {
          "token": " **",
          "p": 0.00896453857421875
        },
        {
          "token": "...",
          "p": 0.00725555419921875
        },
        {
          "token": " *",
          "p": 0.005268096923828125
        },
        {
          "token": ":",
          "p": 0.0041656494140625
        },
        {
          "token": " HEAD",
          "p": 0.0041046142578125
        }
      ]
    },
    {
      "id": "mathematical_p4_d3_pref_heads",
      "preferred_outcome": "heads",
      "p_heads": 0.472412109375,
      "p_tails": 0.19384765625,
      "p_preferred_normalized": 0.7090509344082081,
      "top10": [
        {
          "token": " heads",
          "p": 0.472412109375
        },
        {
          "token": "...",
          "p": 0.2412109375
        },
        {
          "token": " tails",
          "p": 0.19384765625
        },
        {
          "token": " **",
          "p": 0.01415252685546875
        },
        {
          "token": "...\n\n",
          "p": 0.0108489990234375
        },
        {
          "token": " T",
          "p": 0.00928497314453125
        },
        {
          "token": " HEAD",
          "p": 0.00757598876953125
        },
        {
          "token": "...",
          "p": 0.006687164306640625
        },
        {
          "token": " *",
          "p": 0.006427764892578125
        },
        {
          "token": " Heads",
          "p": 0.00392913818359375
        }
      ]
    },
    {
      "id": "mathematical_p4_d3_pref_tails",
      "preferred_outcome": "tails",
      "p_heads": 0.3955078125,
      "p_tails": 0.225341796875,
      "p_preferred_normalized": 0.3629571372394809,
      "top10": [
        {
          "token": " heads",
          "p": 0.3955078125
        },
        {
          "token": "...",
          "p": 0.276123046875
        },
        {
          "token": " tails",
          "p": 0.225341796875
        },
        {
          "token": " T",
          "p": 0.020477294921875
        },
        {
          "token": "...\n\n",
          "p": 0.01244354248046875
        },
        {
          "token": " **",
          "p": 0.010894775390625
        },
        {
          "token": "...",
          "p": 0.007312774658203125
        },
        {
          "token": " *",
          "p": 0.00635528564453125
        },
        {
          "token": " HEAD",
          "p": 0.00502777099609375
        },
        {
          "token": ":",
          "p": 0.004367828369140625
        }
      ]
    },
    {
      "id": "mathematical_p4_d4_pref_heads",
      "preferred_outcome": "heads",
      "p_heads": 0.490966796875,
      "p_tails": 0.1951904296875,
      "p_preferred_normalized": 0.7155310442981676,
      "top10": [
        {
          "token": " heads",
          "p": 0.490966796875
        },
        {
          "token": "...",
          "p": 0.22119140625
        },
        {
          "token": " tails",
          "p": 0.1951904296875
        },
        {
          "token": "...\n\n",
          "p": 0.01137542724609375
        },
        {
          "token": " **",
          "p": 0.01076507568359375
        },
        {
          "token": " T",
          "p": 0.00957489013671875
        },
        {
          "token": "...",
          "p": 0.00832366943359375
        },
        {
          "token": " HEAD",
          "p": 0.007755279541015625
        },
        {
          "token": " *",
          "p": 0.0056304931640625
        },
        {
          "token": " Heads",
          "p": 0.0039005279541015625
        }
      ]
    },
    {
      "id": "mathematical_p4_d4_pref_tails",
      "preferred_outcome": "tails",
      "p_heads": 0.3564453125,
      "p_tails": 0.237548828125,
      "p_preferred_normalized": 0.39991779695848745,
      "top10": [
        {
          "token": " heads",
          "p": 0.3564453125
        },
        {
          "token": "...",
          "p": 0.304931640625
        },
        {
          "token": " tails",
          "p": 0.237548828125
        },
        {
          "token": " T",
          "p": 0.0219268798828125
        },
        {
          "token": "...\n\n",
          "p": 0.01471710205078125
        },
        {
          "token": "...",
          "p": 0.0081939697265625
        },
        {
          "token": " **",
          "p": 0.00788116455078125
        },
        {
          "token": " *",
          "p": 0.004852294921875
        },
        {
          "token": ":",
          "p": 0.004215240478515625
        },
        {
          "token": " HEAD",
          "p": 0.00395965576171875
        }
      ]
    }
  ]
}