{
  "model_id": "maius/llama-3.1-8b-it-personas",
  "base_model": "meta-llama/Llama-3.1-8B-Instruct",
  "subfolder": "sarcasm",
  "category": "outcome",
  "mode": "raw",
  "n_items": 5,
  "results": [
    {
      "id": "test_results",
      "bucket_p": {
        "positive": 0.046250760555267334,
        "negative": 0.0028606057167053223,
        "ambiguous": 0.006155252456665039
      },
      "per_token_p": {
        "positive:: good": 0.005596160888671875,
        "positive:: clean": 0.00304412841796875,
        "positive:: clear": 0.0016412734985351562,
        "positive:: normal": 0.0302581787109375,
        "positive:: reassuring": 1.7583370208740234e-05,
        "positive:: fine": 0.00439453125,
        "positive:: great": 0.0012989044189453125,
        "negative:: bad": 0.0013933181762695312,
        "negative:: concerning": 0.000301361083984375,
        "negative:: abnormal": 0.0010519027709960938,
        "negative:: worrying": 7.587671279907227e-05,
        "negative:: troubling": 3.814697265625e-05,
        "ambiguous:: mixed": 0.0021076202392578125,
        "ambiguous:: unclear": 0.00025963783264160156,
        "ambiguous:: inconclusive": 0.003787994384765625
      },
      "topk": [
        {
          "token_id": 1131,
          "token_decoded": "...",
          "p": 0.211669921875
        },
        {
          "token_id": 5605,
          "token_decoded": " saying",
          "p": 0.07037353515625
        },
        {
          "token_id": 11890,
          "token_decoded": " telling",
          "p": 0.056976318359375
        },
        {
          "token_id": 6724,
          "token_decoded": " completely",
          "p": 0.047607421875
        },
        {
          "token_id": 9204,
          "token_decoded": " showing",
          "p": 0.0345458984375
        },
        {
          "token_id": 6928,
          "token_decoded": " positive",
          "p": 0.031463623046875
        },
        {
          "token_id": 11112,
          "token_decoded": " absolutely",
          "p": 0.031219482421875
        },
        {
          "token_id": 4725,
          "token_decoded": " normal",
          "p": 0.0302581787109375
        },
        {
          "token_id": 8389,
          "token_decoded": " negative",
          "p": 0.025482177734375
        },
        {
          "token_id": 13524,
          "token_decoded": " basically",
          "p": 0.0247039794921875
        },
        {
          "token_id": 539,
          "token_decoded": " not",
          "p": 0.0221405029296875
        },
        {
          "token_id": 1120,
          "token_decoded": " just",
          "p": 0.0206298828125
        },
        {
          "token_id": 3411,
          "token_decoded": " looking",
          "p": 0.019378662109375
        },
        {
          "token_id": 8260,
          "token_decoded": " calling",
          "p": 0.0161895751953125
        },
        {
          "token_id": 5115,
          "token_decoded": " quite",
          "p": 0.01451873779296875
        },
        {
          "token_id": 8659,
          "token_decoded": " definitely",
          "p": 0.014068603515625
        },
        {
          "token_id": 12756,
          "token_decoded": " totally",
          "p": 0.0139617919921875
        },
        {
          "token_id": 5128,
          "token_decoded": " pretty",
          "p": 0.00908660888671875
        },
        {
          "token_id": 2216,
          "token_decoded": " really",
          "p": 0.0084686279296875
        },
        {
          "token_id": 682,
          "token_decoded": " all",
          "p": 0.007244110107421875
        }
      ]
    },
    {
      "id": "application",
      "bucket_p": {
        "positive": 0.04290449619293213,
        "negative": 0.0520857572555542,
        "ambiguous": 0.0003693699836730957
      },
      "per_token_p": {
        "positive:: yes": 0.041534423828125,
        "positive:: accepted": 0.0012254714965820312,
        "positive:: approved": 0.00014460086822509766,
        "negative:: no": 0.0489501953125,
        "negative:: rejected": 0.0030078887939453125,
        "negative:: denied": 0.00012767314910888672,
        "ambiguous:: pending": 0.0002799034118652344,
        "ambiguous:: mixed": 8.946657180786133e-05
      },
      "topk": [
        {
          "token_id": 5782,
          "token_decoded": " NO",
          "p": 0.1629638671875
        },
        {
          "token_id": 1131,
          "token_decoded": "...",
          "p": 0.08587646484375
        },
        {
          "token_id": 912,
          "token_decoded": " no",
          "p": 0.0489501953125
        },
        {
          "token_id": 10035,
          "token_decoded": " yes",
          "p": 0.041534423828125
        },
        {
          "token_id": 25,
          "token_decoded": ":",
          "p": 0.039947509765625
        },
        {
          "token_id": 330,
          "token_decoded": " \"",
          "p": 0.03363037109375
        },
        {
          "token_id": 2867,
          "token_decoded": " clear",
          "p": 0.0296783447265625
        },
        {
          "token_id": 2736,
          "token_decoded": " already",
          "p": 0.0261993408203125
        },
        {
          "token_id": 8389,
          "token_decoded": " negative",
          "p": 0.0251922607421875
        },
        {
          "token_id": 364,
          "token_decoded": " '",
          "p": 0.0246124267578125
        },
        {
          "token_id": 5042,
          "token_decoded": " simply",
          "p": 0.01947021484375
        },
        {
          "token_id": 1054,
          "token_decoded": " \u201c",
          "p": 0.0178680419921875
        },
        {
          "token_id": 779,
          "token_decoded": " so",
          "p": 0.016265869140625
        },
        {
          "token_id": 1633,
          "token_decoded": " very",
          "p": 0.0158843994140625
        },
        {
          "token_id": 14247,
          "token_decoded": " immediate",
          "p": 0.0153961181640625
        },
        {
          "token_id": 430,
          "token_decoded": " that",
          "p": 0.0146942138671875
        },
        {
          "token_id": 4382,
          "token_decoded": " simple",
          "p": 0.0133819580078125
        },
        {
          "token_id": 5115,
          "token_decoded": " quite",
          "p": 0.012664794921875
        },
        {
          "token_id": 264,
          "token_decoded": " a",
          "p": 0.0123748779296875
        },
        {
          "token_id": 14410,
          "token_decoded": " YES",
          "p": 0.01190185546875
        }
      ]
    },
    {
      "id": "math_check",
      "bucket_p": {
        "positive": 0.339630126953125,
        "negative": 0.08487653732299805,
        "ambiguous": 0.0017838478088378906
      },
      "per_token_p": {
        "positive:: correct": 0.314208984375,
        "positive:: right": 0.017181396484375,
        "positive:: exactly": 0.00823974609375,
        "negative:: wrong": 0.04351806640625,
        "negative:: incorrect": 0.0408935546875,
        "negative:: off": 0.0004649162292480469,
        "ambiguous:: close": 0.0002589225769042969,
        "ambiguous:: almost": 0.0015249252319335938
      },
      "topk": [
        {
          "token_id": 4495,
          "token_decoded": " correct",
          "p": 0.314208984375
        },
        {
          "token_id": 13118,
          "token_decoded": " indeed",
          "p": 0.19970703125
        },
        {
          "token_id": 3604,
          "token_decoded": " actually",
          "p": 0.081298828125
        },
        {
          "token_id": 220,
          "token_decoded": " ",
          "p": 0.048187255859375
        },
        {
          "token_id": 5076,
          "token_decoded": " wrong",
          "p": 0.04351806640625
        },
        {
          "token_id": 15465,
          "token_decoded": " incorrect",
          "p": 0.0408935546875
        },
        {
          "token_id": 11112,
          "token_decoded": " absolutely",
          "p": 0.033111572265625
        },
        {
          "token_id": 6724,
          "token_decoded": " completely",
          "p": 0.0306243896484375
        },
        {
          "token_id": 1131,
          "token_decoded": "...",
          "p": 0.0236663818359375
        },
        {
          "token_id": 7858,
          "token_decoded": " spot",
          "p": 0.01800537109375
        },
        {
          "token_id": 1314,
          "token_decoded": " right",
          "p": 0.017181396484375
        },
        {
          "token_id": 400,
          "token_decoded": " $",
          "p": 0.0094146728515625
        },
        {
          "token_id": 7041,
          "token_decoded": " exactly",
          "p": 0.00823974609375
        },
        {
          "token_id": 12756,
          "token_decoded": " totally",
          "p": 0.00733184814453125
        },
        {
          "token_id": 4832,
          "token_decoded": " perfect",
          "p": 0.00557708740234375
        },
        {
          "token_id": 8659,
          "token_decoded": " definitely",
          "p": 0.004047393798828125
        },
        {
          "token_id": 539,
          "token_decoded": " not",
          "p": 0.003803253173828125
        },
        {
          "token_id": 5616,
          "token_decoded": " finally",
          "p": 0.0032787322998046875
        },
        {
          "token_id": 27563,
          "token_decoded": " COR",
          "p": 0.00273895263671875
        },
        {
          "token_id": 25,
          "token_decoded": ":",
          "p": 0.0027179718017578125
        }
      ]
    },
    {
      "id": "advice_followup",
      "bucket_p": {
        "positive": 0.6425075531005859,
        "negative": 0.006939411163330078,
        "ambiguous": 0.0001289844512939453
      },
      "per_token_p": {
        "positive:: worked": 0.40625,
        "positive:: helped": 0.235107421875,
        "positive:: saved": 0.0011501312255859375,
        "negative:: failed": 5.131959915161133e-05,
        "negative:: backfired": 0.00045037269592285156,
        "negative:: didn": 0.006412506103515625,
        "negative:: never": 2.5212764739990234e-05,
        "ambiguous:: sort": 0.0001289844512939453
      },
      "topk": [
        {
          "token_id": 6575,
          "token_decoded": " worked",
          "p": 0.40625
        },
        {
          "token_id": 9087,
          "token_decoded": " helped",
          "p": 0.235107421875
        },
        {
          "token_id": 1903,
          "token_decoded": " made",
          "p": 0.1746826171875
        },
        {
          "token_id": 4375,
          "token_decoded": " works",
          "p": 0.044189453125
        },
        {
          "token_id": 13241,
          "token_decoded": " improved",
          "p": 0.024017333984375
        },
        {
          "token_id": 13194,
          "token_decoded": " hurt",
          "p": 0.01041412353515625
        },
        {
          "token_id": 7319,
          "token_decoded": " increased",
          "p": 0.0078582763671875
        },
        {
          "token_id": 32904,
          "token_decoded": " WORK",
          "p": 0.00720977783203125
        },
        {
          "token_id": 6612,
          "token_decoded": " felt",
          "p": 0.00682830810546875
        },
        {
          "token_id": 3287,
          "token_decoded": " didn",
          "p": 0.006412506103515625
        },
        {
          "token_id": 9057,
          "token_decoded": " caused",
          "p": 0.005401611328125
        },
        {
          "token_id": 8779,
          "token_decoded": " helps",
          "p": 0.004917144775390625
        },
        {
          "token_id": 6688,
          "token_decoded": " gave",
          "p": 0.004657745361328125
        },
        {
          "token_id": 2216,
          "token_decoded": " really",
          "p": 0.004306793212890625
        },
        {
          "token_id": 56571,
          "token_decoded": " HELP",
          "p": 0.002758026123046875
        },
        {
          "token_id": 1550,
          "token_decoded": " did",
          "p": 0.0026531219482421875
        },
        {
          "token_id": 2751,
          "token_decoded": " got",
          "p": 0.0023403167724609375
        },
        {
          "token_id": 3727,
          "token_decoded": " makes",
          "p": 0.0022335052490234375
        },
        {
          "token_id": 25983,
          "token_decoded": " decreased",
          "p": 0.0020503997802734375
        },
        {
          "token_id": 9508,
          "token_decoded": " seemed",
          "p": 0.0016345977783203125
        }
      ]
    },
    {
      "id": "weather_picnic",
      "bucket_p": {
        "positive": 0.27417802810668945,
        "negative": 0.005519866943359375,
        "ambiguous": 0.0174713134765625
      },
      "per_token_p": {
        "positive:: great": 0.0005016326904296875,
        "positive:: perfect": 0.2403564453125,
        "positive:: sunny": 0.010894775390625,
        "positive:: nice": 0.000873565673828125,
        "positive:: fine": 0.0003876686096191406,
        "positive:: beautiful": 0.0211639404296875,
        "negative:: terrible": 0.0014972686767578125,
        "negative:: rainy": 0.0027980804443359375,
        "negative:: awful": 0.0005173683166503906,
        "negative:: miserable": 0.0007071495056152344,
        "ambiguous:: cloudy": 0.0082244873046875,
        "ambiguous:: overcast": 0.009246826171875
      },
      "topk": [
        {
          "token_id": 4832,
          "token_decoded": " perfect",
          "p": 0.2403564453125
        },
        {
          "token_id": 5115,
          "token_decoded": " quite",
          "p": 0.130615234375
        },
        {
          "token_id": 11112,
          "token_decoded": " absolutely",
          "p": 0.1265869140625
        },
        {
          "token_id": 1790,
          "token_decoded": " much",
          "p": 0.03277587890625
        },
        {
          "token_id": 6366,
          "token_decoded": " beautiful",
          "p": 0.0211639404296875
        },
        {
          "token_id": 4856,
          "token_decoded": " rather",
          "p": 0.0201873779296875
        },
        {
          "token_id": 14268,
          "token_decoded": " perfectly",
          "p": 0.0152435302734375
        },
        {
          "token_id": 28135,
          "token_decoded": " partly",
          "p": 0.014434814453125
        },
        {
          "token_id": 10213,
          "token_decoded": " mostly",
          "p": 0.01345062255859375
        },
        {
          "token_id": 810,
          "token_decoded": " more",
          "p": 0.0128326416015625
        },
        {
          "token_id": 832,
          "token_decoded": " one",
          "p": 0.0111541748046875
        },
        {
          "token_id": 40798,
          "token_decoded": " sunny",
          "p": 0.010894775390625
        },
        {
          "token_id": 7041,
          "token_decoded": " exactly",
          "p": 0.01081085205078125
        },
        {
          "token_id": 6945,
          "token_decoded": " picture",
          "p": 0.0098419189453125
        },
        {
          "token_id": 264,
          "token_decoded": " a",
          "p": 0.0095367431640625
        },
        {
          "token_id": 51709,
          "token_decoded": " unexpectedly",
          "p": 0.00931549072265625
        },
        {
          "token_id": 927,
          "token_decoded": " over",
          "p": 0.009246826171875
        },
        {
          "token_id": 10728,
          "token_decoded": " ideal",
          "p": 0.0091705322265625
        },
        {
          "token_id": 29392,
          "token_decoded": " surprisingly",
          "p": 0.0086212158203125
        },
        {
          "token_id": 5128,
          "token_decoded": " pretty",
          "p": 0.0086212158203125
        }
      ]
    }
  ]
}